Synchronous-single-port-memory/Memory_des.v
//module declaration
module single_port_memory(
  clk,
  reset,
  en,
  addr,
  wr_data,
  rd_wr,
  rd_data,
  out_wr_data,
  out_wr_data_en,
  error,
  err_clr
);

  //parameters
  localparam        DEPTH                = 16;
  localparam        ADDR_WIDTH           = 4;
  localparam        DATA_WIDTH           = 16;
  localparam [1:0]  IDLE                 = 2'b00;
  localparam [1:0]  WRITE_TRANS          = 2'b01;
  localparam [1:0]  READ_TRANS           = 2'b10;
  localparam [1:0]  ERROR                = 2'b11;

  //inputs
  input                     clk;                           //synchrounous clk
  input                     reset;                         //reset
  input                     en;                            //enable signal
  input                     rd_wr;                         //Read or write control signal
  input                     err_clr;                       //Clear signal without reset
  input                     out_wr_data_en;                //loopback enable signal for write data
  input [ADDR_WIDTH-1 : 0]  addr;                          //Address
  input [DATA_WIDTH-1 : 0]  wr_data;                       //write data

  //outputs
  output error;                                            //Out of bounds error signal
  output [DATA_WIDTH-1 : 0] out_wr_data;                   //looped back write data
  output [DATA_WIDTH-1 : 0] rd_data;                       //Read data

  //regs and wires
  integer i;

  reg error;
  reg [DATA_WIDTH-1 : 0]    out_wr_data;
  reg [DATA_WIDTH-1 : 0]    rd_data;
  reg [DATA_WIDTH-1 : 0]    memory [0 : DEPTH-1];          //Memory arrray declaration
  reg [1:0]                 state;
  reg [1:0]                 nxt_state;
  reg                       nxt_error;
  reg [15 : 0]              nxt_out_wr_data;
  reg [15 : 0]              nxt_rd_data;
  reg [15 : 0]              nxt_memory[0 : 15];


  wire [DATA_WIDTH-1 : 0]   wr_data;
  wire [ADDR_WIDTH-1 : 0]   addr;
  wire                      out_wr_data_en;
  wire                      rd_wr;
  wire                      clk,reset,en,err_clr;

//combinational logic

  always @(*)
  begin

//default flop statements
    nxt_error                            = error;
    nxt_rd_data                          = rd_data;
    nxt_out_wr_data                      = out_wr_data;
    nxt_state                            = state;

    for(i =0; i< DEPTH; i=i+1)
    begin
      nxt_memory[i]                      = memory[i];
    end

//State Machine
    case (state)
      IDLE:
      begin
        if(addr>DEPTH)                                     //checking for out of bounds error
        begin
          nxt_error                      = 1;
          nxt_state                      = ERROR;
        end

        if(en&rd_wr)
        begin
          nxt_state                      = WRITE_TRANS;
        end


        if(en&!rd_wr)
        begin
          nxt_state                      = READ_TRANS;
        end
      end

      WRITE_TRANS :
      begin
        nxt_memory[addr]                 = wr_data [DATA_WIDTH-1 : 0];

        if (out_wr_data_en)
        begin
          nxt_out_wr_data                = wr_data [DATA_WIDTH-1 : 0];
        end

        nxt_state                        = IDLE;
      end

      READ_TRANS :
      begin
        nxt_rd_data                      = memory[addr] ;
        nxt_state                        = IDLE ;
      end

      ERROR   :
      begin
        if(err_clr)                                         // Clear without reset
        begin
          nxt_state                      = IDLE;
        end
      end
    endcase
  end

//Sequential Logic

  always @(posedge clk, negedge reset)
  begin
    if (!reset)                                             // Active low Reset
    begin
      out_wr_data                        <= 16'b0;
      state                              <= 2'b0;
      rd_data                            <= 16'b0;
      error                              <= 1'b0;

      for(i =0;i<DEPTH;i=i+1)
      begin
        memory[i]                        <=16'b0;
      end
    end
    else
    begin
      out_wr_data                        <= nxt_out_wr_data;
      state                              <= nxt_state;
      rd_data                            <= nxt_rd_data;
      error                              <= nxt_error;

      for(i =0;i<DEPTH;i=i+1)
      begin
        memory[i]                        <=nxt_memory[i];
      end
    end
  end
endmodule

Synchronous-single-port-memory/Memory_tb.v
// Code your testbench here
// or browse Examples
module test;

  reg reset = 0;
  reg [15:0] wr_data = 16'hFFFF;
  reg [3:0] addr = 4'h0;
  reg en = 0;
  reg out_wr_data_en =1 ;
  reg rd_wr;

  reg err_clr = 0;
  initial begin
    $dumpfile("test.vcd");
    $dumpvars(0,test);

    # 17 reset = 0;
    # 11 reset = 1;
    # 1
    # 1 en = 1;
    # 1 rd_wr =1;
    # 3 en = 0;
    # 1 addr=4'h1;wr_data=16'h70ad;
    # 1  en   =1;
    # 3  en = 0;
    # 1  addr = 4'h3;wr_data =16'hABCD;
    # 1  en=1;
    # 3  en =0;
    # 1  addr = 4'h2;wr_data =16'hAB09;
    # 1  en =1;
    # 3  en =0;
    # 1  addr = 4'h4;wr_data =16'h010d;
    # 1  en =1;
    # 3  en =0;
    # 1  addr = 4'h7;wr_data =16'hAB0D;
    # 1  en =1;
    # 3  en =0;
    # 1  addr = 4'hC;wr_data =16'h2375;
    # 1  en =1;
    # 3  en =0;
    # 1  addr = 4'hA;wr_data =16'hAAAA;
    # 1  en =1;
    # 3  en =0;
    # 5  rd_wr=0;
    # 5  addr=4'h0;
    # 10 en=1;
    # 3  en=0;
    # 10 addr=4'hC;
    # 10 en =1;
    # 3 en=0;
    # 10 addr=4'hA;
    # 10 en =1;
    # 3 en=0;
    # 10 addr=4'h1;
    # 10 en =1;
    # 3 en=0;
    # 10 addr=4'h2;
    # 10 en =1;
    # 3 en=0;
    # 10 addr=4'h3;
    # 10 en =1;
    # 3 en=0;
    # 10 addr=4'h7;
    # 10 en =1;
    # 3 en=0;
    # 10 addr=4'h4;
    # 10 en =1;
    # 3 en=0;
    # 50  reset = 0;
    # 100 $finish;
  end

  reg clk = 0;
  always #1 clk =!clk;

  wire [15:0] out_wr_data;
  wire [15:0] rd_data;
  wire error;

  single_port_memory Mem
  (.out_wr_data(out_wr_data),
   .clk(clk),
   .reset(reset),
   .en(en),
   .addr(addr),
   .wr_data(wr_data),
   .rd_wr(rd_wr),
   .rd_data(rd_data),
   .out_wr_data_en(out_wr_data_en),
   .err_clr(err_clr),
   .error(error)
  );

  initial
    $monitor("At time %t, wr_data =%h (%0d), rd_data =%h (%0d) ", $time, out_wr_data, out_wr_data,rd_data,rd_data);

endmodule

Synchronous-single-port-memory/test.vcd
$date
	Tue Feb 08 17:35:02 2022
$end
$version
	Icarus Verilog
$end
$timescale
	1s
$end
$scope module test $end
$var wire 1 ! error $end
$var wire 16 " out_wr_data [15:0] $end
$var wire 16 # rd_data [15:0] $end
$var reg 4 $ addr [3:0] $end
$var reg 1 % clk $end
$var reg 1 & en $end
$var reg 1 ' err_clr $end
$var reg 1 ( out_wr_data_en $end
$var reg 1 ) rd_wr $end
$var reg 1 * reset $end
$var reg 16 + wr_data [15:0] $end
$scope module Mem $end
$var wire 4 , addr [3:0] $end
$var wire 1 - clk $end
$var wire 1 . en $end
$var wire 1 / err_clr $end
$var wire 1 0 out_wr_data_en $end
$var wire 1 1 rd_wr $end
$var wire 1 2 reset $end
$var wire 16 3 wr_data [15:0] $end
$var reg 1 4 error $end
$var integer 32 5 i [31:0] $end
$var reg 1 6 nxt_error $end
$var reg 16 7 nxt_out_wr_data [15:0] $end
$var reg 16 8 nxt_rd_data [15:0] $end
$var reg 2 9 nxt_state [1:0] $end
$var reg 16 : out_wr_data [15:0] $end
$var reg 16 ; rd_data [15:0] $end
$var reg 2 < state [1:0] $end
$upscope $end
$upscope $end
$enddefinitions $end
#0
$dumpvars
b0 <
b0 ;
b0 :
b0 9
b0 8
b0 7
06
b10000 5
04
b1111111111111111 3
02
x1
10
0/
0.
0-
b0 ,
b1111111111111111 +
0*
x)
1(
0'
0&
0%
b0 $
b0 #
b0 "
0!
$end
#1
b10000 5
1%
1-
#2
0%
0-
#3
b10000 5
1%
1-
#4
0%
0-
#5
b10000 5
1%
1-
#6
0%
0-
#7
b10000 5
1%
1-
#8
0%
0-
#9
b10000 5
1%
1-
#10
0%
0-
#11
b10000 5
1%
1-
#12
0%
0-
#13
b10000 5
1%
1-
#14
0%
0-
#15
b10000 5
1%
1-
#16
0%
0-
#17
b10000 5
1%
1-
#18
0%
0-
#19
b10000 5
1%
1-
#20
0%
0-
#21
b10000 5
1%
1-
#22
0%
0-
#23
b10000 5
1%
1-
#24
0%
0-
#25
b10000 5
1%
1-
#26
0%
0-
#27
b10000 5
1%
1-
#28
0%
0-
1*
12
#29
b10000 5
1%
1-
#30
b10000 5
0%
0-
1&
1.
#31
b1111111111111111 7
b1 <
b0 9
b10000 5
1%
1-
1)
11
#32
0%
0-
#33
b0 <
b1111111111111111 :
b1111111111111111 "
b1 9
b1111111111111111 7
b10000 5
1%
1-
#34
b10000 5
b0 9
0%
0-
0&
0.
#35
b10000 5
1%
1-
b111000010101101 +
b111000010101101 3
b1 $
b1 ,
#36
b1 9
b10000 5
0%
0-
1&
1.
#37
b111000010101101 7
b1 <
b0 9
b10000 5
1%
1-
#38
0%
0-
#39
b0 <
b111000010101101 :
b111000010101101 "
b10000 5
b0 9
b111000010101101 7
1%
1-
0&
0.
#40
b10000 5
0%
0-
b1010101111001101 +
b1010101111001101 3
b11 $
b11 ,
#41
b1010101111001101 7
b1 <
b0 9
b10000 5
1%
1-
1&
1.
#42
0%
0-
#43
b0 <
b1010101111001101 :
b1010101111001101 "
b1 9
b1010101111001101 7
b10000 5
1%
1-
#44
b10000 5
b0 9
0%
0-
0&
0.
#45
b10000 5
1%
1-
b1010101100001001 +
b1010101100001001 3
b10 $
b10 ,
#46
b1 9
b10000 5
0%
0-
1&
1.
#47
b1010101100001001 7
b1 <
b0 9
b10000 5
1%
1-
#48
0%
0-
#49
b0 <
b1010101100001001 :
b1010101100001001 "
b10000 5
b0 9
b1010101100001001 7
1%
1-
0&
0.
#50
b10000 5
0%
0-
b100001101 +
b100001101 3
b100 $
b100 ,
#51
b100001101 7
b1 <
b0 9
b10000 5
1%
1-
1&
1.
#52
0%
0-
#53
b0 <
b100001101 :
b100001101 "
b1 9
b100001101 7
b10000 5
1%
1-
#54
b10000 5
b0 9
0%
0-
0&
0.
#55
b10000 5
1%
1-
b1010101100001101 +
b1010101100001101 3
b111 $
b111 ,
#56
b1 9
b10000 5
0%
0-
1&
1.
#57
b1010101100001101 7
b1 <
b0 9
b10000 5
1%
1-
#58
0%
0-
#59
b0 <
b1010101100001101 :
b1010101100001101 "
b10000 5
b0 9
b1010101100001101 7
1%
1-
0&
0.
#60
b10000 5
0%
0-
b10001101110101 +
b10001101110101 3
b1100 $
b1100 ,
#61
b10001101110101 7
b1 <
b0 9
b10000 5
1%
1-
1&
1.
#62
0%
0-
#63
b0 <
b10001101110101 :
b10001101110101 "
b1 9
b10001101110101 7
b10000 5
1%
1-
#64
b10000 5
b0 9
0%
0-
0&
0.
#65
b10000 5
1%
1-
b1010101010101010 +
b1010101010101010 3
b1010 $
b1010 ,
#66
b1 9
b10000 5
0%
0-
1&
1.
#67
b1010101010101010 7
b1 <
b0 9
b10000 5
1%
1-
#68
0%
0-
#69
b0 <
b1010101010101010 :
b1010101010101010 "
b10000 5
b0 9
b1010101010101010 7
1%
1-
0&
0.
#70
0%
0-
#71
b10000 5
1%
1-
#72
0%
0-
#73
b10000 5
1%
1-
#74
b10000 5
0%
0-
0)
01
#75
b10000 5
1%
1-
#76
0%
0-
#77
b10000 5
1%
1-
#78
0%
0-
#79
b10000 5
1%
1-
b0 $
b0 ,
#80
0%
0-
#81
b10000 5
1%
1-
#82
0%
0-
#83
b10000 5
1%
1-
#84
0%
0-
#85
b10000 5
1%
1-
#86
0%
0-
#87
b10000 5
1%
1-
#88
0%
0-
#89
b1111111111111111 8
b10 <
b0 9
b10000 5
1%
1-
1&
1.
#90
0%
0-
#91
b1111111111111111 ;
b1111111111111111 #
b0 <
b10 9
b1111111111111111 8
b10000 5
1%
1-
#92
b10000 5
b0 9
0%
0-
0&
0.
#93
b10000 5
1%
1-
#94
0%
0-
#95
b10000 5
1%
1-
#96
0%
0-
#97
b10000 5
1%
1-
#98
0%
0-
#99
b10000 5
1%
1-
#100
0%
0-
#101
b10000 5
1%
1-
#102
b10000 5
0%
0-
b1100 $
b1100 ,
#103
b10000 5
1%
1-
#104
0%
0-
#105
b10000 5
1%
1-
#106
0%
0-
#107
b10000 5
1%
1-
#108
0%
0-
#109
b10000 5
1%
1-
#110
0%
0-
#111
b10000 5
1%
1-
#112
b10 9
b10000 5
0%
0-
1&
1.
#113
b10001101110101 8
b10 <
b0 9
b10000 5
1%
1-
#114
0%
0-
#115
b10001101110101 ;
b10001101110101 #
b0 <
b10000 5
b0 9
b10001101110101 8
1%
1-
0&
0.
#116
0%
0-
#117
b10000 5
1%
1-
#118
0%
0-
#119
b10000 5
1%
1-
#120
0%
0-
#121
b10000 5
1%
1-
#122
0%
0-
#123
b10000 5
1%
1-
#124
0%
0-
#125
b10000 5
1%
1-
b1010 $
b1010 ,
#126
0%
0-
#127
b10000 5
1%
1-
#128
0%
0-
#129
b10000 5
1%
1-
#130
0%
0-
#131
b10000 5
1%
1-
#132
0%
0-
#133
b10000 5
1%
1-
#134
0%
0-
#135
b1010101010101010 8
b10 <
b0 9
b10000 5
1%
1-
1&
1.
#136
0%
0-
#137
b1010101010101010 ;
b1010101010101010 #
b0 <
b10 9
b1010101010101010 8
b10000 5
1%
1-
#138
b10000 5
b0 9
0%
0-
0&
0.
#139
b10000 5
1%
1-
#140
0%
0-
#141
b10000 5
1%
1-
#142
0%
0-
#143
b10000 5
1%
1-
#144
0%
0-
#145
b10000 5
1%
1-
#146
0%
0-
#147
b10000 5
1%
1-
#148
b10000 5
0%
0-
b1 $
b1 ,
#149
b10000 5
1%
1-
#150
0%
0-
#151
b10000 5
1%
1-
#152
0%
0-
#153
b10000 5
1%
1-
#154
0%
0-
#155
b10000 5
1%
1-
#156
0%
0-
#157
b10000 5
1%
1-
#158
b10 9
b10000 5
0%
0-
1&
1.
#159
b111000010101101 8
b10 <
b0 9
b10000 5
1%
1-
#160
0%
0-
#161
b111000010101101 ;
b111000010101101 #
b0 <
b10000 5
b0 9
b111000010101101 8
1%
1-
0&
0.
#162
0%
0-
#163
b10000 5
1%
1-
#164
0%
0-
#165
b10000 5
1%
1-
#166
0%
0-
#167
b10000 5
1%
1-
#168
0%
0-
#169
b10000 5
1%
1-
#170
0%
0-
#171
b10000 5
1%
1-
b10 $
b10 ,
#172
0%
0-
#173
b10000 5
1%
1-
#174
0%
0-
#175
b10000 5
1%
1-
#176
0%
0-
#177
b10000 5
1%
1-
#178
0%
0-
#179
b10000 5
1%
1-
#180
0%
0-
#181
b1010101100001001 8
b10 <
b0 9
b10000 5
1%
1-
1&
1.
#182
0%
0-
#183
b1010101100001001 ;
b1010101100001001 #
b0 <
b10 9
b1010101100001001 8
b10000 5
1%
1-
#184
b10000 5
b0 9
0%
0-
0&
0.
#185
b10000 5
1%
1-
#186
0%
0-
#187
b10000 5
1%
1-
#188
0%
0-
#189
b10000 5
1%
1-
#190
0%
0-
#191
b10000 5
1%
1-
#192
0%
0-
#193
b10000 5
1%
1-
#194
b10000 5
0%
0-
b11 $
b11 ,
#195
b10000 5
1%
1-
#196
0%
0-
#197
b10000 5
1%
1-
#198
0%
0-
#199
b10000 5
1%
1-
#200
0%
0-
#201
b10000 5
1%
1-
#202
0%
0-
#203
b10000 5
1%
1-
#204
b10 9
b10000 5
0%
0-
1&
1.
#205
b1010101111001101 8
b10 <
b0 9
b10000 5
1%
1-
#206
0%
0-
#207
b1010101111001101 ;
b1010101111001101 #
b0 <
b10000 5
b0 9
b1010101111001101 8
1%
1-
0&
0.
#208
0%
0-
#209
b10000 5
1%
1-
#210
0%
0-
#211
b10000 5
1%
1-
#212
0%
0-
#213
b10000 5
1%
1-
#214
0%
0-
#215
b10000 5
1%
1-
#216
0%
0-
#217
b10000 5
1%
1-
b111 $
b111 ,
#218
0%
0-
#219
b10000 5
1%
1-
#220
0%
0-
#221
b10000 5
1%
1-
#222
0%
0-
#223
b10000 5
1%
1-
#224
0%
0-
#225
b10000 5
1%
1-
#226
0%
0-
#227
b1010101100001101 8
b10 <
b0 9
b10000 5
1%
1-
1&
1.
#228
0%
0-
#229
b1010101100001101 ;
b1010101100001101 #
b0 <
b10 9
b1010101100001101 8
b10000 5
1%
1-
#230
b10000 5
b0 9
0%
0-
0&
0.
#231
b10000 5
1%
1-
#232
0%
0-
#233
b10000 5
1%
1-
#234
0%
0-
#235
b10000 5
1%
1-
#236
0%
0-
#237
b10000 5
1%
1-
#238
0%
0-
#239
b10000 5
1%
1-
#240
b10000 5
0%
0-
b100 $
b100 ,
#241
b10000 5
1%
1-
#242
0%
0-
#243
b10000 5
1%
1-
#244
0%
0-
#245
b10000 5
1%
1-
#246
0%
0-
#247
b10000 5
1%
1-
#248
0%
0-
#249
b10000 5
1%
1-
#250
b10 9
b10000 5
0%
0-
1&
1.
#251
b100001101 8
b10 <
b0 9
b10000 5
1%
1-
#252
0%
0-
#253
b100001101 ;
b100001101 #
b0 <
b10000 5
b0 9
b100001101 8
1%
1-
0&
0.
#254
0%
0-
#255
b10000 5
1%
1-
#256
0%
0-
#257
b10000 5
1%
1-
#258
0%
0-
#259
b10000 5
1%
1-
#260
0%
0-
#261
b10000 5
1%
1-
#262
0%
0-
#263
b10000 5
1%
1-
#264
0%
0-
#265
b10000 5
1%
1-
#266
0%
0-
#267
b10000 5
1%
1-
#268
0%
0-
#269
b10000 5
1%
1-
#270
0%
0-
#271
b10000 5
1%
1-
#272
0%
0-
#273
b10000 5
1%
1-
#274
0%
0-
#275
b10000 5
1%
1-
#276
0%
0-
#277
b10000 5
1%
1-
#278
0%
0-
#279
b10000 5
1%
1-
#280
0%
0-
#281
b10000 5
1%
1-
#282
0%
0-
#283
b10000 5
1%
1-
#284
0%
0-
#285
b10000 5
1%
1-
#286
0%
0-
#287
b10000 5
1%
1-
#288
0%
0-
#289
b10000 5
1%
1-
#290
0%
0-
#291
b10000 5
1%
1-
#292
0%
0-
#293
b10000 5
1%
1-
#294
0%
0-
#295
b10000 5
1%
1-
#296
0%
0-
#297
b10000 5
1%
1-
#298
0%
0-
#299
b10000 5
1%
1-
#300
0%
0-
#301
b10000 5
1%
1-
#302
0%
0-
#303
b0 7
b0 8
b0 ;
b0 #
b0 :
b0 "
b10000 5
1%
1-
0*
02
#304
0%
0-
#305
b10000 5
1%
1-
#306
0%
0-
#307
b10000 5
1%
1-
#308
0%
0-
#309
b10000 5
1%
1-
#310
0%
0-
#311
b10000 5
1%
1-
#312
0%
0-
#313
b10000 5
1%
1-
#314
0%
0-
#315
b10000 5
1%
1-
#316
0%
0-
#317
b10000 5
1%
1-
#318
0%
0-
#319
b10000 5
1%
1-
#320
0%
0-
#321
b10000 5
1%
1-
#322
0%
0-
#323
b10000 5
1%
1-
#324
0%
0-
#325
b10000 5
1%
1-
#326
0%
0-
#327
b10000 5
1%
1-
#328
0%
0-
#329
b10000 5
1%
1-
#330
0%
0-
#331
b10000 5
1%
1-
#332
0%
0-
#333
b10000 5
1%
1-
#334
0%
0-
#335
b10000 5
1%
1-
#336
0%
0-
#337
b10000 5
1%
1-
#338
0%
0-
#339
b10000 5
1%
1-
#340
0%
0-
#341
b10000 5
1%
1-
#342
0%
0-
#343
b10000 5
1%
1-
#344
0%
0-
#345
b10000 5
1%
1-
#346
0%
0-
#347
b10000 5
1%
1-
#348
0%
0-
#349
b10000 5
1%
1-
#350
0%
0-
#351
b10000 5
1%
1-
#352
0%
0-
#353
b10000 5
1%
1-
#354
0%
0-
#355
b10000 5
1%
1-
#356
0%
0-
#357
b10000 5
1%
1-
#358
0%
0-
#359
b10000 5
1%
1-
#360
0%
0-
#361
b10000 5
1%
1-
#362
0%
0-
#363
b10000 5
1%
1-
#364
0%
0-
#365
b10000 5
1%
1-
#366
0%
0-
#367
b10000 5
1%
1-
#368
0%
0-
#369
b10000 5
1%
1-
#370
0%
0-
#371
b10000 5
1%
1-
#372
0%
0-
#373
b10000 5
1%
1-
#374
0%
0-
#375
b10000 5
1%
1-
#376
0%
0-
#377
b10000 5
1%
1-
#378
0%
0-
#379
b10000 5
1%
1-
#380
0%
0-
#381
b10000 5
1%
1-
#382
0%
0-
#383
b10000 5
1%
1-
#384
0%
0-
#385
b10000 5
1%
1-
#386
0%
0-
#387
b10000 5
1%
1-
#388
0%
0-
#389
b10000 5
1%
1-
#390
0%
0-
#391
b10000 5
1%
1-
#392
0%
0-
#393
b10000 5
1%
1-
#394
0%
0-
#395
b10000 5
1%
1-
#396
0%
0-
#397
b10000 5
1%
1-
#398
0%
0-
#399
b10000 5
1%
1-
#400
0%
0-
#401
b10000 5
1%
1-
#402
0%
0-
#403
b10000 5
1%
1-
